LICENSE.md
MANIFEST.in
README.md
setup.py
btrm.egg-info/PKG-INFO
btrm.egg-info/SOURCES.txt
btrm.egg-info/dependency_links.txt
btrm.egg-info/entry_points.txt
btrm.egg-info/requires.txt
btrm.egg-info/top_level.txt
sources/__init__.py
sources/btrm.py
sources/config/btrm.conf
sources/resources/argument-object/description.txt
sources/resources/argument-object/epilog.txt
sources/resources/argument-object/usage.txt
sources/resources/argument-object/version.txt
sources/resources/images/recover_example.png
sources/resources/images/remove_example.png
sources/resources/images/show_list.png